DirectReport/__init__.py
DirectReport/__main__.py
DirectReport/browserview/__init__.py
DirectReport/browserview/app.py
DirectReport/browserview/static/css/main.css
DirectReport/browserview/static/js/index.js
DirectReport/browserview/templates/404.html
DirectReport/browserview/templates/base.html
DirectReport/browserview/templates/detail.html
DirectReport/browserview/templates/index.html
DirectReport/browserview/templates/list.html
DirectReport/commandline/__init__.py
DirectReport/commandline/commandline.py
DirectReport/database/__init__.py
DirectReport/database/blocker_storage.py
DirectReport/database/daily_storage.py
DirectReport/database/entry_storage.py
DirectReport/database/jira_storage.py
DirectReport/database/note_storage.py
DirectReport/database/weekly_storage.py
DirectReport/models/__init__.py
DirectReport/models/daily_builder.py
DirectReport/models/entry.py
DirectReport/models/list_builder.py
DirectReport/models/weekly_builder.py
DirectReport/models/blocker_models/__init__.py
DirectReport/models/blocker_models/block_builder.py
DirectReport/models/blocker_models/blocker.py
DirectReport/models/jira_models/__init__.py
DirectReport/models/jira_models/jira.py
DirectReport/models/jira_models/jira_builder.py
DirectReport/models/note/__init__.py
DirectReport/models/note/note.py
DirectReport/models/note/note_builder.py
DirectReport/tests/test_commandline.py
DirectReport/tests/test_db.py
DirectReport/tests/test_jira_data_store.py
DirectReport/tests/test_list_builder.py
DirectReport/tests/test_model.py
DirectReport/tests/test_web.py
DirectReport/tests/test_weekly_storage.py
DirectReport-1.0.0.dist-info/LICENSE
DirectReport-1.0.0.dist-info/METADATA
DirectReport-1.0.0.dist-info/WHEEL
DirectReport-1.0.0.dist-info/top_level.txt
DirectReport-1.0.0.dist-info/RECORD
